LICENSE
MANIFEST.in
README.rst
setup.py
smachine/__init__.py
smachine/tests.py
smachine.egg-info/PKG-INFO
smachine.egg-info/SOURCES.txt
smachine.egg-info/dependency_links.txt
smachine.egg-info/top_level.txt