Metadata-Version: 1.0
Name: smachine
Version: 0.1
Summary: Simple finite state machine.
Home-page: https://github.com/caffeinehit/smachine
Author: Alen Mujezinovic
Author-email: alen@caffeinehit.com
License: UNKNOWN
Keywords: finite state machine fsm
Platform: UNKNOWN
Classifier: Development Status :: 5 - Production/Stable
Classifier: Environment :: Console
Classifier: Environment :: MacOS X
Classifier: Environment :: Web Environment
Classifier: Environment :: Other Environment
Classifier: Environment :: X11 Applications
Classifier: Intended Audience :: Developers
Classifier: Operating System :: OS Independent
Classifier: Programming Language :: Python
Classifier: Topic :: Utilities
